<?xml version="1.0" encoding="UTF-8"?>
<Indirizzi xmlns:xsi="http://www.w3.org/2001/XMLSchema-instance" xsi:noNamespaceSchemaLocation="Indirizzi.xsd"><Utente><Email>alicewhite@gmail.com</Email><Indirizzo><Via>milano</Via><Numero_civico>80</Numero_civico><Città>Padova</Città><Provincia>Montegrotto</Provincia><CAP>35036</CAP></Indirizzo>
<Indirizzo><Via>kingscross</Via><Numero_civico>80</Numero_civico><Città>paington</Città><Provincia>Torquay</Provincia><CAP>35100</CAP></Indirizzo></Utente></Indirizzi>
